{
  "canonical_id": "larrys-mabiala",
  "canonical_name": "Larrys Mabiala",
  "positions": [
    "CB"
  ],
  "leagues": [
    "MLS"
  ],
  "sport_names": [],
  "ambiguous": false,
  "appearances": [
    {
      "id": 1509015,
      "full_name": "Larrys Mabiala",
      "team": "",
      "position": "CB",
      "sport_id": null,
      "league": "MLS",
      "jersey": null,
      "college": null,
      "college_stats": null,
      "height": "6'2\"",
      "weight": "176",
      "college_full": null
    }
  ],
  "career_totals": {
    "minutes_played": 14101.0,
    "shots": 91.0,
    "shots_on_target": 27.0,
    "goals": 12.0,
    "xg": 10.078,
    "xg_place": 0.29019999999999985,
    "goals_minus_xg": 1.9219999999999997,
    "key_passes": 17.0,
    "assists": 2.0,
    "xa": 1.5962,
    "assists_minus_xa": 0.4038000000000001,
    "goals_plus_assists": 14.0,
    "xg_plus_xa": 11.6743,
    "points_added": 3.4379,
    "xpoints_added": 5.474,
    "passes_attempted": 6119.0,
    "pass_completion_pct": 6.791600000000001,
    "xpass_completion_pct": 6.6675,
    "passes_over_expected": 103.1865,
    "passes_over_expected_p100": 12.409,
    "avg_pass_distance": 182.5927,
    "avg_pass_vertical": 68.51570000000001
  },
  "season_totals": {
    "MLS-2017": {
      "minutes_played": 1309.0,
      "shots": 9.0,
      "shots_on_target": 0.0,
      "goals": 0.0,
      "xg": 0.688,
      "xg_place": -0.688,
      "goals_minus_xg": -0.688,
      "key_passes": 0.0,
      "assists": 0.0,
      "xa": 0.0,
      "assists_minus_xa": 0.0,
      "goals_plus_assists": 0.0,
      "xg_plus_xa": 0.688,
      "points_added": 0.0,
      "xpoints_added": 0.4089,
      "passes_attempted": 572.0,
      "pass_completion_pct": 0.8304,
      "xpass_completion_pct": 0.8104,
      "passes_over_expected": 11.4424,
      "passes_over_expected_p100": 2.0004,
      "avg_pass_distance": 22.3843,
      "avg_pass_vertical": 9.2146
    },
    "MLS-2018": {
      "minutes_played": 3323.0,
      "shots": 27.0,
      "shots_on_target": 12.0,
      "goals": 5.0,
      "xg": 2.6495,
      "xg_place": 1.7381,
      "goals_minus_xg": 2.3505,
      "key_passes": 5.0,
      "assists": 1.0,
      "xa": 0.4174,
      "assists_minus_xa": 0.5826,
      "goals_plus_assists": 6.0,
      "xg_plus_xa": 3.0668,
      "points_added": 1.8766,
      "xpoints_added": 1.5896,
      "passes_attempted": 1303.0,
      "pass_completion_pct": 0.835,
      "xpass_completion_pct": 0.8037,
      "passes_over_expected": 40.8319,
      "passes_over_expected_p100": 3.1337,
      "avg_pass_distance": 22.986,
      "avg_pass_vertical": 10.6935
    },
    "MLS-2019": {
      "minutes_played": 2204.0,
      "shots": 22.0,
      "shots_on_target": 7.0,
      "goals": 2.0,
      "xg": 2.1859,
      "xg_place": -0.1186,
      "goals_minus_xg": -0.1859,
      "key_passes": 2.0,
      "assists": 0.0,
      "xa": 0.1535,
      "assists_minus_xa": -0.1535,
      "goals_plus_assists": 2.0,
      "xg_plus_xa": 2.3394,
      "points_added": 0.9563,
      "xpoints_added": 1.2372,
      "passes_attempted": 887.0,
      "pass_completion_pct": 0.8365,
      "xpass_completion_pct": 0.8264,
      "passes_over_expected": 9.002,
      "passes_over_expected_p100": 1.0149,
      "avg_pass_distance": 21.8117,
      "avg_pass_vertical": 7.6623
    },
    "MLS-2020": {
      "minutes_played": 1984.0,
      "shots": 8.0,
      "shots_on_target": 3.0,
      "goals": 2.0,
      "xg": 1.3326,
      "xg_place": -0.2519,
      "goals_minus_xg": 0.6674,
      "key_passes": 1.0,
      "assists": 0.0,
      "xa": 0.0949,
      "assists_minus_xa": -0.0949,
      "goals_plus_assists": 2.0,
      "xg_plus_xa": 1.4275,
      "points_added": 0.0152,
      "xpoints_added": 0.335,
      "passes_attempted": 863.0,
      "pass_completion_pct": 0.8505,
      "xpass_completion_pct": 0.8392,
      "passes_over_expected": 9.7583,
      "passes_over_expected_p100": 1.1307,
      "avg_pass_distance": 24.2067,
      "avg_pass_vertical": 8.112
    },
    "MLS-2021": {
      "minutes_played": 2488.0,
      "shots": 12.0,
      "shots_on_target": 3.0,
      "goals": 2.0,
      "xg": 1.3746,
      "xg_place": 0.2221,
      "goals_minus_xg": 0.6254,
      "key_passes": 6.0,
      "assists": 1.0,
      "xa": 0.7995,
      "assists_minus_xa": 0.2005,
      "goals_plus_assists": 3.0,
      "xg_plus_xa": 2.1741,
      "points_added": 0.0,
      "xpoints_added": 0.5165,
      "passes_attempted": 1135.0,
      "pass_completion_pct": 0.8529,
      "xpass_completion_pct": 0.836,
      "passes_over_expected": 19.0841,
      "passes_over_expected_p100": 1.6814,
      "avg_pass_distance": 23.5165,
      "avg_pass_vertical": 7.7167
    },
    "MLS-2022": {
      "minutes_played": 1731.0,
      "shots": 5.0,
      "shots_on_target": 1.0,
      "goals": 0.0,
      "xg": 0.2282,
      "xg_place": 0.2752,
      "goals_minus_xg": -0.2282,
      "key_passes": 2.0,
      "assists": 0.0,
      "xa": 0.104,
      "assists_minus_xa": -0.104,
      "goals_plus_assists": 0.0,
      "xg_plus_xa": 0.3323,
      "points_added": 0.0,
      "xpoints_added": 0.1624,
      "passes_attempted": 851.0,
      "pass_completion_pct": 0.8402,
      "xpass_completion_pct": 0.8312,
      "passes_over_expected": 7.6324,
      "passes_over_expected_p100": 0.8969,
      "avg_pass_distance": 23.1905,
      "avg_pass_vertical": 8.2432
    },
    "MLS-2023": {
      "minutes_played": 1014.0,
      "shots": 7.0,
      "shots_on_target": 1.0,
      "goals": 1.0,
      "xg": 1.5754,
      "xg_place": -0.8429,
      "goals_minus_xg": -0.5754,
      "key_passes": 1.0,
      "assists": 0.0,
      "xa": 0.0269,
      "assists_minus_xa": -0.0269,
      "goals_plus_assists": 1.0,
      "xg_plus_xa": 1.6024,
      "points_added": 0.5898,
      "xpoints_added": 1.2062,
      "passes_attempted": 467.0,
      "pass_completion_pct": 0.8437,
      "xpass_completion_pct": 0.8334,
      "passes_over_expected": 4.812,
      "passes_over_expected_p100": 1.0304,
      "avg_pass_distance": 24.6214,
      "avg_pass_vertical": 7.6771
    },
    "MLS-2024": {
      "minutes_played": 48.0,
      "shots": 1.0,
      "shots_on_target": 0.0,
      "goals": 0.0,
      "xg": 0.0438,
      "xg_place": -0.0438,
      "goals_minus_xg": -0.0438,
      "key_passes": 0.0,
      "assists": 0.0,
      "xa": 0.0,
      "assists_minus_xa": 0.0,
      "goals_plus_assists": 0.0,
      "xg_plus_xa": 0.0438,
      "points_added": 0.0,
      "xpoints_added": 0.0182,
      "passes_attempted": 41.0,
      "pass_completion_pct": 0.9024,
      "xpass_completion_pct": 0.8872,
      "passes_over_expected": 0.6234,
      "passes_over_expected_p100": 1.5206,
      "avg_pass_distance": 19.8756,
      "avg_pass_vertical": 9.1963
    }
  },
  "season_coaches": {},
  "game_log": [
    {
      "game_id": "soccer-mls-2017-WBLMvYAQxe",
      "game_slug": "soccer-mls-2017-wblmvyaqxe",
      "display": "MLS 2017 Season",
      "season": 2017,
      "week": 1,
      "league": "MLS",
      "sport_slug": "mls-2017",
      "away_team": "",
      "home_team": "",
      "date_str": "",
      "score_home": "",
      "score_away": "",
      "stats": {
        "minutes_played": 1309.0,
        "shots": 9.0,
        "shots_on_target": 0.0,
        "goals": 0.0,
        "xg": 0.688,
        "xg_place": -0.688,
        "goals_minus_xg": -0.688,
        "key_passes": 0.0,
        "assists": 0.0,
        "xa": 0.0,
        "assists_minus_xa": 0.0,
        "goals_plus_assists": 0.0,
        "xg_plus_xa": 0.688,
        "points_added": 0.0,
        "xpoints_added": 0.4089,
        "passes_attempted": 572.0,
        "pass_completion_pct": 0.8304,
        "xpass_completion_pct": 0.8104,
        "passes_over_expected": 11.4424,
        "passes_over_expected_p100": 2.0004,
        "avg_pass_distance": 22.3843,
        "avg_pass_vertical": 9.2146
      }
    },
    {
      "game_id": "soccer-mls-2018-WBLMvYAQxe",
      "game_slug": "soccer-mls-2018-wblmvyaqxe",
      "display": "MLS 2018 Season",
      "season": 2018,
      "week": 1,
      "league": "MLS",
      "sport_slug": "mls-2018",
      "away_team": "",
      "home_team": "",
      "date_str": "",
      "score_home": "",
      "score_away": "",
      "stats": {
        "minutes_played": 3323.0,
        "shots": 27.0,
        "shots_on_target": 12.0,
        "goals": 5.0,
        "xg": 2.6495,
        "xg_place": 1.7381,
        "goals_minus_xg": 2.3505,
        "key_passes": 5.0,
        "assists": 1.0,
        "xa": 0.4174,
        "assists_minus_xa": 0.5826,
        "goals_plus_assists": 6.0,
        "xg_plus_xa": 3.0668,
        "points_added": 1.8766,
        "xpoints_added": 1.5896,
        "passes_attempted": 1303.0,
        "pass_completion_pct": 0.835,
        "xpass_completion_pct": 0.8037,
        "passes_over_expected": 40.8319,
        "passes_over_expected_p100": 3.1337,
        "avg_pass_distance": 22.986,
        "avg_pass_vertical": 10.6935
      }
    },
    {
      "game_id": "soccer-mls-2019-WBLMvYAQxe",
      "game_slug": "soccer-mls-2019-wblmvyaqxe",
      "display": "MLS 2019 Season",
      "season": 2019,
      "week": 1,
      "league": "MLS",
      "sport_slug": "mls-2019",
      "away_team": "",
      "home_team": "",
      "date_str": "",
      "score_home": "",
      "score_away": "",
      "stats": {
        "minutes_played": 2204.0,
        "shots": 22.0,
        "shots_on_target": 7.0,
        "goals": 2.0,
        "xg": 2.1859,
        "xg_place": -0.1186,
        "goals_minus_xg": -0.1859,
        "key_passes": 2.0,
        "assists": 0.0,
        "xa": 0.1535,
        "assists_minus_xa": -0.1535,
        "goals_plus_assists": 2.0,
        "xg_plus_xa": 2.3394,
        "points_added": 0.9563,
        "xpoints_added": 1.2372,
        "passes_attempted": 887.0,
        "pass_completion_pct": 0.8365,
        "xpass_completion_pct": 0.8264,
        "passes_over_expected": 9.002,
        "passes_over_expected_p100": 1.0149,
        "avg_pass_distance": 21.8117,
        "avg_pass_vertical": 7.6623
      }
    },
    {
      "game_id": "soccer-mls-2020-WBLMvYAQxe",
      "game_slug": "soccer-mls-2020-wblmvyaqxe",
      "display": "MLS 2020 Season",
      "season": 2020,
      "week": 1,
      "league": "MLS",
      "sport_slug": "mls-2020",
      "away_team": "",
      "home_team": "",
      "date_str": "",
      "score_home": "",
      "score_away": "",
      "stats": {
        "minutes_played": 1984.0,
        "shots": 8.0,
        "shots_on_target": 3.0,
        "goals": 2.0,
        "xg": 1.3326,
        "xg_place": -0.2519,
        "goals_minus_xg": 0.6674,
        "key_passes": 1.0,
        "assists": 0.0,
        "xa": 0.0949,
        "assists_minus_xa": -0.0949,
        "goals_plus_assists": 2.0,
        "xg_plus_xa": 1.4275,
        "points_added": 0.0152,
        "xpoints_added": 0.335,
        "passes_attempted": 863.0,
        "pass_completion_pct": 0.8505,
        "xpass_completion_pct": 0.8392,
        "passes_over_expected": 9.7583,
        "passes_over_expected_p100": 1.1307,
        "avg_pass_distance": 24.2067,
        "avg_pass_vertical": 8.112
      }
    },
    {
      "game_id": "soccer-mls-2021-WBLMvYAQxe",
      "game_slug": "soccer-mls-2021-wblmvyaqxe",
      "display": "MLS 2021 Season",
      "season": 2021,
      "week": 1,
      "league": "MLS",
      "sport_slug": "mls-2021",
      "away_team": "",
      "home_team": "",
      "date_str": "",
      "score_home": "",
      "score_away": "",
      "stats": {
        "minutes_played": 2488.0,
        "shots": 12.0,
        "shots_on_target": 3.0,
        "goals": 2.0,
        "xg": 1.3746,
        "xg_place": 0.2221,
        "goals_minus_xg": 0.6254,
        "key_passes": 6.0,
        "assists": 1.0,
        "xa": 0.7995,
        "assists_minus_xa": 0.2005,
        "goals_plus_assists": 3.0,
        "xg_plus_xa": 2.1741,
        "points_added": 0.0,
        "xpoints_added": 0.5165,
        "passes_attempted": 1135.0,
        "pass_completion_pct": 0.8529,
        "xpass_completion_pct": 0.836,
        "passes_over_expected": 19.0841,
        "passes_over_expected_p100": 1.6814,
        "avg_pass_distance": 23.5165,
        "avg_pass_vertical": 7.7167
      }
    },
    {
      "game_id": "soccer-mls-2022-WBLMvYAQxe",
      "game_slug": "soccer-mls-2022-wblmvyaqxe",
      "display": "MLS 2022 Season",
      "season": 2022,
      "week": 1,
      "league": "MLS",
      "sport_slug": "mls-2022",
      "away_team": "",
      "home_team": "",
      "date_str": "",
      "score_home": "",
      "score_away": "",
      "stats": {
        "minutes_played": 1731.0,
        "shots": 5.0,
        "shots_on_target": 1.0,
        "goals": 0.0,
        "xg": 0.2282,
        "xg_place": 0.2752,
        "goals_minus_xg": -0.2282,
        "key_passes": 2.0,
        "assists": 0.0,
        "xa": 0.104,
        "assists_minus_xa": -0.104,
        "goals_plus_assists": 0.0,
        "xg_plus_xa": 0.3323,
        "points_added": 0.0,
        "xpoints_added": 0.1624,
        "passes_attempted": 851.0,
        "pass_completion_pct": 0.8402,
        "xpass_completion_pct": 0.8312,
        "passes_over_expected": 7.6324,
        "passes_over_expected_p100": 0.8969,
        "avg_pass_distance": 23.1905,
        "avg_pass_vertical": 8.2432
      }
    },
    {
      "game_id": "soccer-mls-2023-WBLMvYAQxe",
      "game_slug": "soccer-mls-2023-wblmvyaqxe",
      "display": "MLS 2023 Season",
      "season": 2023,
      "week": 1,
      "league": "MLS",
      "sport_slug": "mls-2023",
      "away_team": "",
      "home_team": "",
      "date_str": "",
      "score_home": "",
      "score_away": "",
      "stats": {
        "minutes_played": 1014.0,
        "shots": 7.0,
        "shots_on_target": 1.0,
        "goals": 1.0,
        "xg": 1.5754,
        "xg_place": -0.8429,
        "goals_minus_xg": -0.5754,
        "key_passes": 1.0,
        "assists": 0.0,
        "xa": 0.0269,
        "assists_minus_xa": -0.0269,
        "goals_plus_assists": 1.0,
        "xg_plus_xa": 1.6024,
        "points_added": 0.5898,
        "xpoints_added": 1.2062,
        "passes_attempted": 467.0,
        "pass_completion_pct": 0.8437,
        "xpass_completion_pct": 0.8334,
        "passes_over_expected": 4.812,
        "passes_over_expected_p100": 1.0304,
        "avg_pass_distance": 24.6214,
        "avg_pass_vertical": 7.6771
      }
    },
    {
      "game_id": "soccer-mls-2024-WBLMvYAQxe",
      "game_slug": "soccer-mls-2024-wblmvyaqxe",
      "display": "MLS 2024 Season",
      "season": 2024,
      "week": 1,
      "league": "MLS",
      "sport_slug": "mls-2024",
      "away_team": "",
      "home_team": "",
      "date_str": "",
      "score_home": "",
      "score_away": "",
      "stats": {
        "minutes_played": 48.0,
        "shots": 1.0,
        "shots_on_target": 0.0,
        "goals": 0.0,
        "xg": 0.0438,
        "xg_place": -0.0438,
        "goals_minus_xg": -0.0438,
        "key_passes": 0.0,
        "assists": 0.0,
        "xa": 0.0,
        "assists_minus_xa": 0.0,
        "goals_plus_assists": 0.0,
        "xg_plus_xa": 0.0438,
        "points_added": 0.0,
        "xpoints_added": 0.0182,
        "passes_attempted": 41.0,
        "pass_completion_pct": 0.9024,
        "xpass_completion_pct": 0.8872,
        "passes_over_expected": 0.6234,
        "passes_over_expected_p100": 1.5206,
        "avg_pass_distance": 19.8756,
        "avg_pass_vertical": 9.1963
      }
    }
  ],
  "college": null,
  "nfl": null,
  "articles": []
}