{
  "canonical_id": "wayne-frederick",
  "canonical_name": "Wayne Frederick",
  "positions": [
    "CM"
  ],
  "leagues": [
    "MLSNP"
  ],
  "sport_names": [],
  "ambiguous": false,
  "appearances": [
    {
      "id": 1506276,
      "full_name": "Wayne Frederick",
      "team": "",
      "position": "CM",
      "sport_id": null,
      "league": "MLSNP",
      "jersey": null,
      "college": null,
      "college_stats": null,
      "height": null,
      "weight": null,
      "college_full": null
    }
  ],
  "career_totals": {
    "minutes_played": 2761.0,
    "shots": 27.0,
    "shots_on_target": 8.0,
    "goals": 2.0,
    "xg": 3.0755999999999997,
    "xg_place": -0.7483,
    "goals_minus_xg": -1.0756000000000001,
    "key_passes": 13.0,
    "assists": 4.0,
    "xa": 1.59,
    "assists_minus_xa": 2.41,
    "goals_plus_assists": 6.0,
    "xg_plus_xa": 4.6654,
    "points_added": 1.0592,
    "xpoints_added": 2.2066,
    "passes_attempted": 997.0,
    "pass_completion_pct": 4.3108,
    "xpass_completion_pct": 4.2203,
    "passes_over_expected": -9.885100000000001,
    "passes_over_expected_p100": 9.044899999999998,
    "avg_pass_distance": 87.65610000000001,
    "avg_pass_vertical": 31.1344
  },
  "season_totals": {
    "MLS-2024": {
      "minutes_played": 4.0,
      "shots": 0.0,
      "shots_on_target": 0.0,
      "goals": 0.0,
      "xg": 0.0,
      "xg_place": 0.0,
      "goals_minus_xg": 0.0,
      "key_passes": 0.0,
      "assists": 0.0,
      "xa": 0.0,
      "assists_minus_xa": 0.0,
      "goals_plus_assists": 0.0,
      "xg_plus_xa": 0.0,
      "points_added": 0.0,
      "xpoints_added": 0.0,
      "passes_attempted": 1.0,
      "pass_completion_pct": 1.0,
      "xpass_completion_pct": 0.9031,
      "passes_over_expected": 0.0969,
      "passes_over_expected_p100": 9.6875,
      "avg_pass_distance": 23.5808,
      "avg_pass_vertical": 19.32
    },
    "MLSNP-2024": {
      "minutes_played": 1233.0,
      "shots": 18.0,
      "shots_on_target": 6.0,
      "goals": 1.0,
      "xg": 1.9655,
      "xg_place": -0.5376,
      "goals_minus_xg": -0.9655,
      "key_passes": 6.0,
      "assists": 2.0,
      "xa": 0.685,
      "assists_minus_xa": 1.315,
      "goals_plus_assists": 3.0,
      "xg_plus_xa": 2.6504,
      "points_added": 0.6153,
      "xpoints_added": 1.5705,
      "passes_attempted": 409.0,
      "pass_completion_pct": 0.78,
      "xpass_completion_pct": 0.8141,
      "passes_over_expected": -13.9663,
      "passes_over_expected_p100": -3.4147,
      "avg_pass_distance": 16.9865,
      "avg_pass_vertical": 4.8072
    },
    "MLS-2025": {
      "minutes_played": 273.0,
      "shots": 2.0,
      "shots_on_target": 0.0,
      "goals": 0.0,
      "xg": 0.1447,
      "xg_place": -0.1447,
      "goals_minus_xg": -0.1447,
      "key_passes": 0.0,
      "assists": 0.0,
      "xa": 0.0,
      "assists_minus_xa": 0.0,
      "goals_plus_assists": 0.0,
      "xg_plus_xa": 0.1447,
      "points_added": 0.0,
      "xpoints_added": 0.2124,
      "passes_attempted": 90.0,
      "pass_completion_pct": 0.8333,
      "xpass_completion_pct": 0.8185,
      "passes_over_expected": 1.3386,
      "passes_over_expected_p100": 1.4874,
      "avg_pass_distance": 14.5618,
      "avg_pass_vertical": 3.0473
    },
    "MLSNP-2025": {
      "minutes_played": 454.0,
      "shots": 1.0,
      "shots_on_target": 1.0,
      "goals": 0.0,
      "xg": 0.0303,
      "xg_place": 0.0122,
      "goals_minus_xg": -0.0303,
      "key_passes": 4.0,
      "assists": 1.0,
      "xa": 0.581,
      "assists_minus_xa": 0.419,
      "goals_plus_assists": 1.0,
      "xg_plus_xa": 0.6113,
      "points_added": 0.0,
      "xpoints_added": 0.0067,
      "passes_attempted": 220.0,
      "pass_completion_pct": 0.8455,
      "xpass_completion_pct": 0.8294,
      "passes_over_expected": 3.523,
      "passes_over_expected_p100": 1.6014,
      "avg_pass_distance": 16.7662,
      "avg_pass_vertical": 4.1261
    },
    "MLS-2026": {
      "minutes_played": 797.0,
      "shots": 6.0,
      "shots_on_target": 1.0,
      "goals": 1.0,
      "xg": 0.9351,
      "xg_place": -0.0782,
      "goals_minus_xg": 0.0649,
      "key_passes": 3.0,
      "assists": 1.0,
      "xa": 0.324,
      "assists_minus_xa": 0.676,
      "goals_plus_assists": 2.0,
      "xg_plus_xa": 1.259,
      "points_added": 0.4439,
      "xpoints_added": 0.417,
      "passes_attempted": 277.0,
      "pass_completion_pct": 0.852,
      "xpass_completion_pct": 0.8552,
      "passes_over_expected": -0.8773,
      "passes_over_expected_p100": -0.3167,
      "avg_pass_distance": 15.7608,
      "avg_pass_vertical": -0.1662
    }
  },
  "game_log": [
    {
      "game_id": "soccer-mls-2024-pzeQZ6xQKw",
      "game_slug": "soccer-mls-2024-pzeqz6xqkw",
      "display": "MLS 2024 Season",
      "season": 2024,
      "week": 1,
      "league": "MLS",
      "sport_slug": "mls-2024",
      "away_team": "",
      "home_team": "",
      "date_str": "",
      "score_home": "",
      "score_away": "",
      "stats": {
        "minutes_played": 4.0,
        "shots": 0.0,
        "shots_on_target": 0.0,
        "goals": 0.0,
        "xg": 0.0,
        "xg_place": 0.0,
        "goals_minus_xg": 0.0,
        "key_passes": 0.0,
        "assists": 0.0,
        "xa": 0.0,
        "assists_minus_xa": 0.0,
        "goals_plus_assists": 0.0,
        "xg_plus_xa": 0.0,
        "points_added": 0.0,
        "xpoints_added": 0.0,
        "passes_attempted": 1.0,
        "pass_completion_pct": 1.0,
        "xpass_completion_pct": 0.9031,
        "passes_over_expected": 0.0969,
        "passes_over_expected_p100": 9.6875,
        "avg_pass_distance": 23.5808,
        "avg_pass_vertical": 19.32
      }
    },
    {
      "game_id": "soccer-mlsnp-2024-7VqG1oWMvW",
      "game_slug": "soccer-mlsnp-2024-7vqg1owmvw",
      "display": "MLSNP 2024 Season",
      "season": 2024,
      "week": 1,
      "league": "MLSNP",
      "sport_slug": "mlsnp-2024",
      "away_team": "",
      "home_team": "",
      "date_str": "",
      "score_home": "",
      "score_away": "",
      "stats": {
        "minutes_played": 1233.0,
        "shots": 18.0,
        "shots_on_target": 6.0,
        "goals": 1.0,
        "xg": 1.9655,
        "xg_place": -0.5376,
        "goals_minus_xg": -0.9655,
        "key_passes": 6.0,
        "assists": 2.0,
        "xa": 0.685,
        "assists_minus_xa": 1.315,
        "goals_plus_assists": 3.0,
        "xg_plus_xa": 2.6504,
        "points_added": 0.6153,
        "xpoints_added": 1.5705,
        "passes_attempted": 409.0,
        "pass_completion_pct": 0.78,
        "xpass_completion_pct": 0.8141,
        "passes_over_expected": -13.9663,
        "passes_over_expected_p100": -3.4147,
        "avg_pass_distance": 16.9865,
        "avg_pass_vertical": 4.8072
      }
    },
    {
      "game_id": "soccer-mls-2025-pzeQZ6xQKw",
      "game_slug": "soccer-mls-2025-pzeqz6xqkw",
      "display": "MLS 2025 Season",
      "season": 2025,
      "week": 1,
      "league": "MLS",
      "sport_slug": "mls-2025",
      "away_team": "",
      "home_team": "",
      "date_str": "",
      "score_home": "",
      "score_away": "",
      "stats": {
        "minutes_played": 273.0,
        "shots": 2.0,
        "shots_on_target": 0.0,
        "goals": 0.0,
        "xg": 0.1447,
        "xg_place": -0.1447,
        "goals_minus_xg": -0.1447,
        "key_passes": 0.0,
        "assists": 0.0,
        "xa": 0.0,
        "assists_minus_xa": 0.0,
        "goals_plus_assists": 0.0,
        "xg_plus_xa": 0.1447,
        "points_added": 0.0,
        "xpoints_added": 0.2124,
        "passes_attempted": 90.0,
        "pass_completion_pct": 0.8333,
        "xpass_completion_pct": 0.8185,
        "passes_over_expected": 1.3386,
        "passes_over_expected_p100": 1.4874,
        "avg_pass_distance": 14.5618,
        "avg_pass_vertical": 3.0473
      }
    },
    {
      "game_id": "soccer-mlsnp-2025-7VqG1oWMvW",
      "game_slug": "soccer-mlsnp-2025-7vqg1owmvw",
      "display": "MLSNP 2025 Season",
      "season": 2025,
      "week": 1,
      "league": "MLSNP",
      "sport_slug": "mlsnp-2025",
      "away_team": "",
      "home_team": "",
      "date_str": "",
      "score_home": "",
      "score_away": "",
      "stats": {
        "minutes_played": 454.0,
        "shots": 1.0,
        "shots_on_target": 1.0,
        "goals": 0.0,
        "xg": 0.0303,
        "xg_place": 0.0122,
        "goals_minus_xg": -0.0303,
        "key_passes": 4.0,
        "assists": 1.0,
        "xa": 0.581,
        "assists_minus_xa": 0.419,
        "goals_plus_assists": 1.0,
        "xg_plus_xa": 0.6113,
        "points_added": 0.0,
        "xpoints_added": 0.0067,
        "passes_attempted": 220.0,
        "pass_completion_pct": 0.8455,
        "xpass_completion_pct": 0.8294,
        "passes_over_expected": 3.523,
        "passes_over_expected_p100": 1.6014,
        "avg_pass_distance": 16.7662,
        "avg_pass_vertical": 4.1261
      }
    },
    {
      "game_id": "soccer-mls-2026-pzeQZ6xQKw",
      "game_slug": "soccer-mls-2026-pzeqz6xqkw",
      "display": "MLS 2026 Season",
      "season": 2026,
      "week": 1,
      "league": "MLS",
      "sport_slug": "mls-2026",
      "away_team": "",
      "home_team": "",
      "date_str": "",
      "score_home": "",
      "score_away": "",
      "stats": {
        "minutes_played": 797.0,
        "shots": 6.0,
        "shots_on_target": 1.0,
        "goals": 1.0,
        "xg": 0.9351,
        "xg_place": -0.0782,
        "goals_minus_xg": 0.0649,
        "key_passes": 3.0,
        "assists": 1.0,
        "xa": 0.324,
        "assists_minus_xa": 0.676,
        "goals_plus_assists": 2.0,
        "xg_plus_xa": 1.259,
        "points_added": 0.4439,
        "xpoints_added": 0.417,
        "passes_attempted": 277.0,
        "pass_completion_pct": 0.852,
        "xpass_completion_pct": 0.8552,
        "passes_over_expected": -0.8773,
        "passes_over_expected_p100": -0.3167,
        "avg_pass_distance": 15.7608,
        "avg_pass_vertical": -0.1662
      }
    }
  ],
  "college": null,
  "nfl": null,
  "articles": []
}