{
  "canonical_id": "yohan-croizet",
  "canonical_name": "Yohan Croizet",
  "positions": [
    "CM"
  ],
  "leagues": [
    "MLS"
  ],
  "sport_names": [],
  "ambiguous": false,
  "appearances": [
    {
      "id": 1508674,
      "full_name": "Yohan Croizet",
      "team": "",
      "position": "CM",
      "sport_id": null,
      "league": "MLS",
      "jersey": null,
      "college": null,
      "college_stats": null,
      "height": "5'10\"",
      "weight": "170",
      "college_full": null
    }
  ],
  "career_totals": {
    "minutes_played": 3104.0,
    "shots": 73.0,
    "shots_on_target": 26.0,
    "goals": 6.0,
    "xg": 6.4892,
    "xg_place": 0.04879999999999998,
    "goals_minus_xg": -0.48919999999999997,
    "key_passes": 42.0,
    "assists": 4.0,
    "xa": 3.4823,
    "assists_minus_xa": 0.5177,
    "goals_plus_assists": 10.0,
    "xg_plus_xa": 9.9716,
    "points_added": 2.3467000000000002,
    "xpoints_added": 3.2298,
    "passes_attempted": 1224.0,
    "pass_completion_pct": 1.5737999999999999,
    "xpass_completion_pct": 1.5674,
    "passes_over_expected": -0.8850999999999996,
    "passes_over_expected_p100": 0.6461999999999999,
    "avg_pass_distance": 39.1706,
    "avg_pass_vertical": 3.1107
  },
  "season_totals": {
    "MLS-2018": {
      "minutes_played": 1891.0,
      "shots": 49.0,
      "shots_on_target": 14.0,
      "goals": 3.0,
      "xg": 4.0423,
      "xg_place": 0.142,
      "goals_minus_xg": -1.0423,
      "key_passes": 30.0,
      "assists": 3.0,
      "xa": 2.6063,
      "assists_minus_xa": 0.3937,
      "goals_plus_assists": 6.0,
      "xg_plus_xa": 6.6487,
      "points_added": 1.1361,
      "xpoints_added": 1.8223,
      "passes_attempted": 776.0,
      "pass_completion_pct": 0.768,
      "xpass_completion_pct": 0.7796,
      "passes_over_expected": -8.9439,
      "passes_over_expected_p100": -1.1526,
      "avg_pass_distance": 19.5585,
      "avg_pass_vertical": 1.2332
    },
    "MLS-2019": {
      "minutes_played": 1213.0,
      "shots": 24.0,
      "shots_on_target": 12.0,
      "goals": 3.0,
      "xg": 2.4469,
      "xg_place": -0.0932,
      "goals_minus_xg": 0.5531,
      "key_passes": 12.0,
      "assists": 1.0,
      "xa": 0.876,
      "assists_minus_xa": 0.124,
      "goals_plus_assists": 4.0,
      "xg_plus_xa": 3.3229,
      "points_added": 1.2106,
      "xpoints_added": 1.4075,
      "passes_attempted": 448.0,
      "pass_completion_pct": 0.8058,
      "xpass_completion_pct": 0.7878,
      "passes_over_expected": 8.0588,
      "passes_over_expected_p100": 1.7988,
      "avg_pass_distance": 19.6121,
      "avg_pass_vertical": 1.8775
    }
  },
  "game_log": [
    {
      "game_id": "soccer-mls-2018-Z2vQ1xlqrA",
      "game_slug": "soccer-mls-2018-z2vq1xlqra",
      "display": "MLS 2018 Season",
      "season": 2018,
      "week": 1,
      "league": "MLS",
      "sport_slug": "mls-2018",
      "away_team": "",
      "home_team": "",
      "date_str": "",
      "score_home": "",
      "score_away": "",
      "stats": {
        "minutes_played": 1891.0,
        "shots": 49.0,
        "shots_on_target": 14.0,
        "goals": 3.0,
        "xg": 4.0423,
        "xg_place": 0.142,
        "goals_minus_xg": -1.0423,
        "key_passes": 30.0,
        "assists": 3.0,
        "xa": 2.6063,
        "assists_minus_xa": 0.3937,
        "goals_plus_assists": 6.0,
        "xg_plus_xa": 6.6487,
        "points_added": 1.1361,
        "xpoints_added": 1.8223,
        "passes_attempted": 776.0,
        "pass_completion_pct": 0.768,
        "xpass_completion_pct": 0.7796,
        "passes_over_expected": -8.9439,
        "passes_over_expected_p100": -1.1526,
        "avg_pass_distance": 19.5585,
        "avg_pass_vertical": 1.2332
      }
    },
    {
      "game_id": "soccer-mls-2019-Z2vQ1xlqrA",
      "game_slug": "soccer-mls-2019-z2vq1xlqra",
      "display": "MLS 2019 Season",
      "season": 2019,
      "week": 1,
      "league": "MLS",
      "sport_slug": "mls-2019",
      "away_team": "",
      "home_team": "",
      "date_str": "",
      "score_home": "",
      "score_away": "",
      "stats": {
        "minutes_played": 1213.0,
        "shots": 24.0,
        "shots_on_target": 12.0,
        "goals": 3.0,
        "xg": 2.4469,
        "xg_place": -0.0932,
        "goals_minus_xg": 0.5531,
        "key_passes": 12.0,
        "assists": 1.0,
        "xa": 0.876,
        "assists_minus_xa": 0.124,
        "goals_plus_assists": 4.0,
        "xg_plus_xa": 3.3229,
        "points_added": 1.2106,
        "xpoints_added": 1.4075,
        "passes_attempted": 448.0,
        "pass_completion_pct": 0.8058,
        "xpass_completion_pct": 0.7878,
        "passes_over_expected": 8.0588,
        "passes_over_expected_p100": 1.7988,
        "avg_pass_distance": 19.6121,
        "avg_pass_vertical": 1.8775
      }
    }
  ],
  "college": null,
  "nfl": null,
  "articles": []
}