<?xml version='1.0' encoding='utf-8'?>
<game>
  <slug>synthetic-audl-w1-nitro</slug>
  <game_id>SYNTHETIC_AUDL_W1_NITRO</game_id>
  <display>AUDL — Wk 1 (NITRO)</display>
  <league>AUDL</league>
  <season />
  <week>1</week>
  <away_team />
  <home_team />
  <date_str />
  <sport_slug>audl</sport_slug>
  <player_count>9</player_count>
  <stat_keys>
    <item>assists</item>
    <item>blocks</item>
    <item>drops</item>
    <item>goals</item>
    <item>throwaways</item>
    <item>yardsReceived</item>
    <item>yardsThrown</item>
  </stat_keys>
  <players>
    <item>
      <canonical_id>chris-larberg</canonical_id>
      <canonical_name>Chris Larberg</canonical_name>
      <positions>
        <item>P</item>
      </positions>
      <ambiguous>False</ambiguous>
      <stats>
        <goals>0.0</goals>
        <assists>0.0</assists>
        <yardsThrown>0.0</yardsThrown>
        <yardsReceived>0.0</yardsReceived>
        <blocks>0.0</blocks>
        <throwaways>0.0</throwaways>
        <drops>0.0</drops>
      </stats>
    </item>
    <item>
      <canonical_id>eli-friedman</canonical_id>
      <canonical_name>Eli Friedman</canonical_name>
      <positions>
        <item>P</item>
      </positions>
      <ambiguous>False</ambiguous>
      <stats>
        <goals>0.0</goals>
        <assists>0.0</assists>
        <yardsThrown>0.0</yardsThrown>
        <yardsReceived>0.0</yardsReceived>
        <blocks>0.0</blocks>
        <throwaways>0.0</throwaways>
        <drops>0.0</drops>
      </stats>
    </item>
    <item>
      <canonical_id>ian-sweeney</canonical_id>
      <canonical_name>Ian Sweeney</canonical_name>
      <positions>
        <item>P</item>
      </positions>
      <ambiguous>False</ambiguous>
      <stats>
        <goals>0.0</goals>
        <assists>0.0</assists>
        <yardsThrown>0.0</yardsThrown>
        <yardsReceived>0.0</yardsReceived>
        <blocks>0.0</blocks>
        <throwaways>0.0</throwaways>
        <drops>0.0</drops>
      </stats>
    </item>
    <item>
      <canonical_id>joshua-moore</canonical_id>
      <canonical_name>Joshua Moore</canonical_name>
      <positions>
        <item>WR</item>
        <item>P</item>
      </positions>
      <ambiguous>False</ambiguous>
      <stats>
        <goals>1.0</goals>
        <assists>0.0</assists>
        <yardsThrown>-4.0</yardsThrown>
        <yardsReceived>85.0</yardsReceived>
        <blocks>1.0</blocks>
        <throwaways>0.0</throwaways>
        <drops>0.0</drops>
      </stats>
    </item>
    <item>
      <canonical_id>kevin-christian</canonical_id>
      <canonical_name>Kevin Christian</canonical_name>
      <positions>
        <item>P</item>
      </positions>
      <ambiguous>False</ambiguous>
      <stats>
        <goals>0.0</goals>
        <assists>1.0</assists>
        <yardsThrown>262.0</yardsThrown>
        <yardsReceived>90.0</yardsReceived>
        <blocks>1.0</blocks>
        <throwaways>3.0</throwaways>
        <drops>0.0</drops>
      </stats>
    </item>
    <item>
      <canonical_id>kuochuan-ponzio</canonical_id>
      <canonical_name>Kuochuan Ponzio</canonical_name>
      <positions>
        <item>P</item>
      </positions>
      <ambiguous>False</ambiguous>
      <stats>
        <goals>0.0</goals>
        <assists>0.0</assists>
        <yardsThrown>0.0</yardsThrown>
        <yardsReceived>0.0</yardsReceived>
        <blocks>0.0</blocks>
        <throwaways>0.0</throwaways>
        <drops>0.0</drops>
      </stats>
    </item>
    <item>
      <canonical_id>leo-pepper</canonical_id>
      <canonical_name>Leo Pepper</canonical_name>
      <positions>
        <item>P</item>
      </positions>
      <ambiguous>False</ambiguous>
      <stats>
        <goals>0.0</goals>
        <assists>0.0</assists>
        <yardsThrown>0.0</yardsThrown>
        <yardsReceived>0.0</yardsReceived>
        <blocks>0.0</blocks>
        <throwaways>0.0</throwaways>
        <drops>0.0</drops>
      </stats>
    </item>
    <item>
      <canonical_id>scott-radlauer</canonical_id>
      <canonical_name>Scott Radlauer</canonical_name>
      <positions>
        <item>P</item>
      </positions>
      <ambiguous>False</ambiguous>
      <stats>
        <goals>0.0</goals>
        <assists>1.0</assists>
        <yardsThrown>53.0</yardsThrown>
        <yardsReceived>6.0</yardsReceived>
        <blocks>1.0</blocks>
        <throwaways>0.0</throwaways>
        <drops>0.0</drops>
      </stats>
    </item>
    <item>
      <canonical_id>tom-doi</canonical_id>
      <canonical_name>Tom Doi</canonical_name>
      <positions>
        <item>P</item>
      </positions>
      <ambiguous>False</ambiguous>
      <stats>
        <goals>0.0</goals>
        <assists>0.0</assists>
        <yardsThrown>0.0</yardsThrown>
        <yardsReceived>0.0</yardsReceived>
        <blocks>0.0</blocks>
        <throwaways>0.0</throwaways>
        <drops>0.0</drops>
      </stats>
    </item>
  </players>
</game>