<?xml version='1.0' encoding='utf-8'?>
<player>
  <canonical_id>cary-angeline-2</canonical_id>
  <canonical_name>Cary Angeline</canonical_name>
  <positions>
    <item>TE</item>
  </positions>
  <leagues />
  <sport_names>
    <item>USFL</item>
  </sport_names>
  <ambiguous>False</ambiguous>
  <appearances>
    <item>
      <id>10545</id>
      <full_name>Cary Angeline</full_name>
      <team />
      <position>TE</position>
      <sport_id>12</sport_id>
      <league />
      <jersey />
      <college />
      <college_stats />
      <height />
      <weight />
    </item>
  </appearances>
  <career_totals />
  <season_totals />
  <game_log />
</player>