<?xml version='1.0' encoding='utf-8'?>
<player>
  <canonical_id>dorian-thompson-robinson-2</canonical_id>
  <canonical_name>Dorian Thompson-Robinson</canonical_name>
  <positions>
    <item>QB</item>
  </positions>
  <leagues />
  <sport_names>
    <item>UFL</item>
  </sport_names>
  <ambiguous>False</ambiguous>
  <appearances>
    <item>
      <id>25652</id>
      <full_name>Dorian Thompson-Robinson</full_name>
      <team>BIRMINGHAM STALLIONS</team>
      <position>QB</position>
      <sport_id>31</sport_id>
      <league />
      <jersey>1</jersey>
      <college />
      <college_stats />
      <height />
      <weight />
    </item>
  </appearances>
  <career_totals>
    <passing_yards>332.0</passing_yards>
    <passing_tds>2.0</passing_tds>
    <interceptions_lost>2.0</interceptions_lost>
    <rushing_yards>49.0</rushing_yards>
    <rushing_tds>1.0</rushing_tds>
    <3pt_pass>1.0</3pt_pass>
  </career_totals>
  <season_totals />
  <game_log />
</player>