<?xml version='1.0' encoding='utf-8'?>
<player>
  <canonical_id>shamarious-gilmore</canonical_id>
  <canonical_name>Shamarious Gilmore</canonical_name>
  <positions>
    <item>OG</item>
  </positions>
  <leagues />
  <sport_names>
    <item>UFL</item>
  </sport_names>
  <ambiguous>False</ambiguous>
  <appearances>
    <item>
      <id>17329</id>
      <full_name>Shamarious Gilmore</full_name>
      <team>ROUGHNECKS</team>
      <position>OG</position>
      <sport_id>19</sport_id>
      <league />
      <jersey />
      <college />
      <college_stats />
      <height />
      <weight />
    </item>
  </appearances>
  <career_totals />
  <season_totals />
  <game_log />
</player>