{
  "slug": "football-elf-2023-230820-milano-seamen-frankfurt-galaxy",
  "game_id": "FOOTBALL_ELF_2023_230820-milano-seamen-frankfurt-galaxy",
  "display": "Milano Seamen @ Frankfurt Galaxy",
  "league": "ELF",
  "season": 2023,
  "week": "12",
  "away_team": "Milano Seamen",
  "home_team": "Frankfurt Galaxy",
  "score_away": 14,
  "score_home": 53,
  "date_str": "2023-08-20",
  "channel": "",
  "record_home": "",
  "record_away": "",
  "sport_slug": "elf-2023",
  "synthetic": false,
  "player_count": 0,
  "stat_keys": [],
  "players": []
}